pySQLExport/__init__.py
pySQLExport/__main__.py
pySQLExport/cli.py
pySQLExport/config.py
pySQLExport/database.py
pySQLExport/export.py
pySQLExport/pySQLExport.py
pySQLExport/utils.py
pySQLExport-0.1.4.dist-info/LICENSE
pySQLExport-0.1.4.dist-info/METADATA
pySQLExport-0.1.4.dist-info/WHEEL
pySQLExport-0.1.4.dist-info/entry_points.txt
pySQLExport-0.1.4.dist-info/top_level.txt
pySQLExport-0.1.4.dist-info/RECORD
