Metadata-Version: 2.1
Name: pySQLExport
Version: 0.1.4
Summary: A command line tool to interact with MySQL databases and export to other formats.
Home-page: https://github.com/aaronlmathis/pySQLExport
Author: Aaron Mathis
Author-email: aaron.mathis@gmail.com
Classifier: Programming Language :: Python :: 3
Classifier: License :: OSI Approved :: MIT License
Classifier: Operating System :: OS Independent
Requires-Python: >=3.6
License-File: LICENSE
Requires-Dist: mysql-connector-python
Requires-Dist: tabulate
Requires-Dist: pandas
Requires-Dist: lxml
Requires-Dist: pyyaml
